LICENSE
MANIFEST.in
README.rst
setup.py
examples/flame_graph.png
nittygriddy/__init__.py
nittygriddy/alienTokenError.py
nittygriddy/datasets.py
nittygriddy/merge.py
nittygriddy/new.py
nittygriddy/parser.py
nittygriddy/profile.py
nittygriddy/run.py
nittygriddy/settings.py
nittygriddy/utils.py
nittygriddy.egg-info/PKG-INFO
nittygriddy.egg-info/SOURCES.txt
nittygriddy.egg-info/dependency_links.txt
nittygriddy.egg-info/requires.txt
nittygriddy.egg-info/top_level.txt
nittygriddy/non-python-files/ConfigureTrain.C
nittygriddy/non-python-files/GetSetting.C
nittygriddy/non-python-files/datasets.yml
nittygriddy/non-python-files/flamegraph.pl
nittygriddy/non-python-files/poormans.sh
nittygriddy/non-python-files/run.C
nittygriddy/non-python-files/stackcollapse-gdb.pl
nittygriddy/tests/__init__.py
nittygriddy/tests/tests.py
scripts/nitty