Metadata-Version: 1.1
Name: nittygriddy
Version: 1.0.5
Summary: Convinient way to deploy your ALICE analysis locally (sequential and proof lite) or on the grid
Home-page: https://github.com/cbourjau/nittygriddy
Author: Christian Bourjau
Author-email: christian.bourjau@cern.ch
License: UNKNOWN
Keywords: alice,cern,grid,proof
Platform: UNKNOWN
Classifier: Programming Language :: Python
Classifier: Programming Language :: Python :: 2.7
Classifier: License :: OSI Approved :: GNU General Public License v3 (GPLv3)
Classifier: Operating System :: OS Independent
Classifier: Intended Audience :: Developers
Classifier: Intended Audience :: Science/Research
Classifier: Topic :: Scientific/Engineering :: Physics
Classifier: Development Status :: 4 - Beta
Classifier: Topic :: Software Development :: Libraries :: Python Modules
